openfiles_ai/__init__.py
openfiles_ai/config.py
openfiles_ai/core/__init__.py
openfiles_ai/core/client.py
openfiles_ai/core/exceptions.py
openfiles_ai/core/generated/__init__.py
openfiles_ai/core/generated/models.py
openfiles_ai/openai/__init__.py
openfiles_ai/openai/client.py
openfiles_ai/tools/__init__.py
openfiles_ai/tools/tools.py
openfiles_ai/utils/__init__.py
openfiles_ai/utils/logger.py
openfiles_ai/utils/path.py
openfiles_ai-0.1.8.dist-info/LICENSE
openfiles_ai-0.1.8.dist-info/METADATA
openfiles_ai-0.1.8.dist-info/WHEEL
openfiles_ai-0.1.8.dist-info/RECORD
