Metadata-Version: 2.3
Name: openfiles-ai
Version: 0.1.8
Summary: OpenFiles SDK - AI-native file storage for your AI agents
License: MIT
Keywords: openfiles,file-storage,ai,sdk,s3-style,version-control
Author: OpenFiles AI
Requires-Python: >=3.9
Classifier: Development Status :: 4 - Beta
Classifier: Intended Audience :: Developers
Classifier: License :: OSI Approved :: MIT License
Classifier: Programming Language :: Python :: 3
Classifier: Programming Language :: Python :: 3.9
Classifier: Programming Language :: Python :: 3.10
Classifier: Programming Language :: Python :: 3.11
Classifier: Programming Language :: Python :: 3.12
Requires-Dist: httpx (>=0.27.0)
Requires-Dist: openai (>=1.101.0)
Requires-Dist: pydantic (>=2.0.0)
Requires-Dist: pydantic-settings (>=2.10.1,<3.0.0)
Requires-Dist: typing-extensions (>=4.0.0)
Project-URL: Documentation, https://github.com/openfiles-ai/openfiles/tree/main/sdks/python
Project-URL: Homepage, https://github.com/openfiles-ai/openfiles
Project-URL: Issues, https://github.com/openfiles-ai/openfiles/issues
Project-URL: Repository, https://github.com/openfiles-ai/openfiles
